molmo_utils/__init__.py
molmo_utils/version.py
molmo_utils/vision_process.py
molmo_utils-0.0.1.dist-info/licenses/LICENSE
molmo_utils-0.0.1.dist-info/METADATA
molmo_utils-0.0.1.dist-info/WHEEL
molmo_utils-0.0.1.dist-info/top_level.txt
molmo_utils-0.0.1.dist-info/RECORD
