Metadata-Version: 2.4
Name: molmo-utils
Version: 0.0.1
Summary: Molmo Utils - PyTorch
Author: Allen Institute for Artificial Intelligence
License:                                  Apache License
Project-URL: Homepage, https://github.com/allenai/molmo-utils
Project-URL: Repository, https://github.com/allenai/molmo-utils
Requires-Python: >=3.10
License-File: LICENSE
Requires-Dist: requests
Requires-Dist: pillow
Requires-Dist: av
Requires-Dist: packaging
Requires-Dist: numpy
Requires-Dist: torch
Requires-Dist: decord2
Provides-Extra: torchcodec
Requires-Dist: torchcodec; extra == "torchcodec"
Dynamic: license-file
